hezarfenai/__init__.py
hezarfenai/models/__init__.py
hezarfenai/models/model_loader.py
hezarfenai/models/news_checker.py
hezarfenai-0.1.3.dist-info/licenses/LICENSE
hezarfenai-0.1.3.dist-info/METADATA
hezarfenai-0.1.3.dist-info/WHEEL
hezarfenai-0.1.3.dist-info/top_level.txt
hezarfenai-0.1.3.dist-info/RECORD
