Metadata-Version: 2.4
Name: hezarfenai
Version: 0.1.3
Summary: A Teknofest project named HezarfenAI Official Python Package
Author: Ömer Asaf Karasu
Author-email: omer.karasu@niafix.com
Classifier: Programming Language :: Python :: 3
Classifier: License :: OSI Approved :: MIT License
Classifier: Operating System :: OS Independent
Requires-Python: >=3.6
License-File: LICENSE
Requires-Dist: nltk>=3.9
Requires-Dist: scikit-learn>=1.0
Requires-Dist: pandas
Requires-Dist: TurkishStemmer
Requires-Dist: numpy
Requires-Dist: scipy
Requires-Dist: joblib
Dynamic: author
Dynamic: author-email
Dynamic: classifier
Dynamic: description
Dynamic: description-content-type
Dynamic: license-file
Dynamic: requires-dist
Dynamic: requires-python
Dynamic: summary
